setup.py
prefetch_generator/__init__.py
prefetch_generator.egg-info/PKG-INFO
prefetch_generator.egg-info/SOURCES.txt
prefetch_generator.egg-info/dependency_links.txt
prefetch_generator.egg-info/top_level.txt