Metadata-Version: 1.1
Name: prefetch-generator
Version: 1.0.0
Summary: a simple tool to compute arbitrary generator in a background thread
Home-page: https://github.com/justheuristic/prefetch_generator
Author: UNKNOWN
Author-email: justheuristic@gmail.com
License: MIT
Keywords: background generator,prefetch generator,parallel generator,prefetch,background,deep learning,theano,tensorflow,lasagne,blocks
Platform: UNKNOWN
Classifier: Development Status :: 5 - Production/Stable
Classifier: Intended Audience :: Science/Research
Classifier: Intended Audience :: Developers
Classifier: Topic :: Scientific/Engineering
Classifier: License :: OSI Approved :: MIT License
Classifier: Programming Language :: Python :: 2.7 
Classifier: Programming Language :: Python :: 3.4 
Classifier: Programming Language :: Python :: 3.5 
